tireKicker/__init__.py
tireKicker/utils.py
tireKicker-0.0.0.dist-info/LICENSE
tireKicker-0.0.0.dist-info/METADATA
tireKicker-0.0.0.dist-info/WHEEL
tireKicker-0.0.0.dist-info/top_level.txt
tireKicker-0.0.0.dist-info/RECORD
