Metadata-Version: 2.1
Name: tireKicker
Version: 0.0.0
Summary: A tool for evaluating the performance of chatbots.
Author: Animesh Nighojkar, Joy Stevenson Boddu
Author-email: John Licato <john@actualization.ai>
License: GNU GENERAL PUBLIC LICENSE
Project-URL: Homepage, https://actualization.ai
Project-URL: Repository, https://github.com/Actualization-AI/tireKicker
Project-URL: Issues, https://github.com/Actualization-AI/tireKicker/issues
Keywords: chatbot,conversational AI,NLP
Classifier: Development Status :: 1 - Planning
Classifier: Environment :: Web Environment
Classifier: Intended Audience :: Information Technology
Classifier: Natural Language :: English
Classifier: Programming Language :: Python :: 3.12
Classifier: Topic :: Communications :: Chat
Classifier: Topic :: Games/Entertainment :: Role-Playing
Classifier: Topic :: Office/Business
Classifier: Topic :: Scientific/Engineering :: Artificial Intelligence
Classifier: Topic :: Other/Nonlisted Topic
Requires-Python: >=3.12
License-File: LICENSE
Requires-Dist: ipywidgets
